hydra_poster/__init__.py
hydra_poster/base.py
hydra_poster/bluesky.py
hydra_poster/exceptions.py
hydra_poster/linkedin.py
hydra_poster/py.typed
hydra_poster/reddit.py
hydra_poster/time_provider.py
hydra_poster/twitter.py
hydra_poster-0.1.1.dist-info/METADATA
hydra_poster-0.1.1.dist-info/WHEEL
hydra_poster-0.1.1.dist-info/RECORD
